ddaptools/__init__.py
ddaptools/dda_constants.py
ddaptools/dda_models-legacy.py
ddaptools/dda_models.py
ddaptools/etl_functions.py
ddaptools/help.py
ddaptools/aws_classes/CommonProcesor.py
ddaptools/aws_classes/JobListener.py
ddaptools/aws_classes/__init__.py
ddaptools/aws_classes/class_adapters.py
ddaptools/aws_classes/class_enhancement-legacy.py
ddaptools/aws_classes/class_enhancement.py
ddaptools/aws_classes/class_guardian.py
ddaptools/aws_classes/class_helpers.py
ddaptools/aws_classes/class_scheduling.py
ddaptools/aws_classes/config_mapper.py
ddaptools/aws_classes/config_mapper_df.py
ddaptools/aws_classes/config_mapper_df_legacy.py
test_scenarios/JobListener.py
test_scenarios/__init__.py
test_scenarios/test_adapters.py
test_scenarios/test_clean_query_demo.py
test_scenarios/test_code.py
test_scenarios/test_common_processing.py
test_scenarios/test_common_processing_test.py
test_scenarios/test_enhancement.py
test_scenarios/test_event_normalization.py
test_scenarios/test_guardian.py
test_scenarios/test_helpers.py
test_scenarios/test_pg_querier.py
test_scenarios/test_run_all_stagings.py
test_scenarios/test_run_all_using_sqs.py
test_scenarios/test_run_all_using_sqs_individual.py
test_scenarios/test_scheduling.py
test_scenarios/test_splitting_algorthm.py
test_scenarios/test_start_staging_list.py
test_scenarios/test_tenth.py
ddaptools-0.4.38.dist-info/LICENSE
ddaptools-0.4.38.dist-info/METADATA
ddaptools-0.4.38.dist-info/WHEEL
ddaptools-0.4.38.dist-info/top_level.txt
ddaptools-0.4.38.dist-info/RECORD
