Metadata-Version: 2.1
Name: ddaptools
Version: 0.4.38
Summary: DDAPP Modules
Author: Anon Dev
License: UNKNOWN
Keywords: python,utilities
Platform: UNKNOWN
Classifier: Development Status :: 1 - Planning
Classifier: Intended Audience :: Developers
Classifier: Programming Language :: Python :: 3
Classifier: Operating System :: Unix
Classifier: Operating System :: MacOS :: MacOS X
Classifier: Operating System :: Microsoft :: Windows
License-File: LICENSE
